mcp_hydrolix/__init__.py
mcp_hydrolix/main.py
mcp_hydrolix/mcp_env.py
mcp_hydrolix/mcp_server.py
mcp_hydrolix/utils.py
mcp_hydrolix/auth/__init__.py
mcp_hydrolix/auth/credentials.py
mcp_hydrolix/auth/mcp_providers.py
mcp_hydrolix/log/__init__.py
mcp_hydrolix/log/log.py
mcp_hydrolix/log/log.yaml
mcp_hydrolix/log/utils.py
mcp_hydrolix-0.1.7.dist-info/METADATA
mcp_hydrolix-0.1.7.dist-info/WHEEL
mcp_hydrolix-0.1.7.dist-info/entry_points.txt
mcp_hydrolix-0.1.7.dist-info/licenses/LICENSE
mcp_hydrolix-0.1.7.dist-info/RECORD
