Metadata-Version: 2.4
Name: mcp-hydrolix
Version: 0.1.7
Summary: An MCP server for Hydrolix.
Project-URL: Home, https://github.com/hydrolix/mcp-hydrolix
License-Expression: Apache-2.0
License-File: LICENSE
Requires-Python: >=3.13
Requires-Dist: certifi>=2026.1.4
Requires-Dist: clickhouse-connect<0.11,>=0.10
Requires-Dist: fastmcp<2.15,>=2.14
Requires-Dist: gunicorn<24.0,>=23.0
Requires-Dist: pip-system-certs<5.0,>=4.0
Requires-Dist: pyjwt<2.11,>=2.10
Requires-Dist: python-dotenv<1.2,>=1.1
Provides-Extra: dev
Requires-Dist: fastapi>=0.124; extra == 'dev'
Requires-Dist: mcp-clickhouse==0.1.13; extra == 'dev'
Requires-Dist: pre-commit; extra == 'dev'
Requires-Dist: pytest; extra == 'dev'
Requires-Dist: pytest-asyncio; extra == 'dev'
Requires-Dist: pytest-repeat; extra == 'dev'
Requires-Dist: pytest-xdist; extra == 'dev'
Requires-Dist: ruff; extra == 'dev'
